drf_versioning/__init__.py
drf_versioning/apps.py
drf_versioning/exceptions.py
drf_versioning/middleware.py
drf_versioning/settings.py
drf_versioning/urls.py
drf_versioning/decorators/__init__.py
drf_versioning/decorators/decorators.py
drf_versioning/decorators/utils.py
drf_versioning/migrations/__init__.py
drf_versioning/serializers/__init__.py
drf_versioning/serializers/utils.py
drf_versioning/serializers/versioned_serializer.py
drf_versioning/transforms/__init__.py
drf_versioning/transforms/common.py
drf_versioning/transforms/transform.py
drf_versioning/versions/__init__.py
drf_versioning/versions/base.py
drf_versioning/versions/serializers.py
drf_versioning/versions/views.py
drf_versioning/views/__init__.py
drf_versioning/views/versioned_viewset.py
djangorestframework_versioning-2.1.0.dist-info/LICENSE
djangorestframework_versioning-2.1.0.dist-info/METADATA
djangorestframework_versioning-2.1.0.dist-info/WHEEL
djangorestframework_versioning-2.1.0.dist-info/top_level.txt
djangorestframework_versioning-2.1.0.dist-info/RECORD
