Metadata-Version: 2.1
Name: djangorestframework-versioning
Version: 2.1.0
Summary: Versioning tools for use with Django Rest Framework
Author-email: Robin Neville <robin.m.neville@gmail.com>
License: MIT License
Project-URL: Homepage,  https://github.com/binnev/djangorestframework_versioning
Keywords: django,REST framework,versioning
Classifier: Programming Language :: Python :: 3
Classifier: License :: OSI Approved :: MIT License
Classifier: Operating System :: OS Independent
Requires-Python: >=3.9
License-File: LICENSE
Requires-Dist: django (>=3.2)
Requires-Dist: djangorestframework (>=3.13.1)
Requires-Dist: typing (>=3.7.4.3)
Requires-Dist: packaging (>=3.0.9)
Provides-Extra: dev
Requires-Dist: black ; extra == 'dev'
Requires-Dist: bumpver ; extra == 'dev'
Requires-Dist: pytest ; extra == 'dev'
